odoo/addons/sale_coupon_order_pending_commercial_partner/README.rst
odoo/addons/sale_coupon_order_pending_commercial_partner/__init__.py
odoo/addons/sale_coupon_order_pending_commercial_partner/__manifest__.py
odoo/addons/sale_coupon_order_pending_commercial_partner/i18n/sale_coupon_order_pending_commercial_partner.pot
odoo/addons/sale_coupon_order_pending_commercial_partner/models/__init__.py
odoo/addons/sale_coupon_order_pending_commercial_partner/models/sale_order.py
odoo/addons/sale_coupon_order_pending_commercial_partner/readme/CONTRIBUTORS.rst
odoo/addons/sale_coupon_order_pending_commercial_partner/readme/DESCRIPTION.rst
odoo/addons/sale_coupon_order_pending_commercial_partner/static/description/icon.png
odoo/addons/sale_coupon_order_pending_commercial_partner/static/description/index.html
odoo/addons/sale_coupon_order_pending_commercial_partner/tests/__init__.py
odoo/addons/sale_coupon_order_pending_commercial_partner/tests/test_sale_coupon_order_pending_commercial_partner.py
odoo13_addon_sale_coupon_order_pending_commercial_partner-13.0.1.0.1.dev2.dist-info/METADATA
odoo13_addon_sale_coupon_order_pending_commercial_partner-13.0.1.0.1.dev2.dist-info/WHEEL
odoo13_addon_sale_coupon_order_pending_commercial_partner-13.0.1.0.1.dev2.dist-info/top_level.txt
odoo13_addon_sale_coupon_order_pending_commercial_partner-13.0.1.0.1.dev2.dist-info/RECORD
