Metadata-Version: 2.1
Name: odoo13-addon-sale-coupon-order-pending-commercial-partner
Version: 13.0.1.0.1.dev2
Summary: Glue module to show pending coupons of the commercial entity
Home-page: https://github.com/OCA/sale-promotion
Author: Tecnativa, Odoo Community Association (OCA)
Author-email: support@odoo-community.org
License: AGPL-3
Platform: UNKNOWN
Classifier: Programming Language :: Python
Classifier: Framework :: Odoo
Classifier: Framework :: Odoo :: 13.0
Classifier: License :: OSI Approved :: GNU Affero General Public License v3
Classifier: Development Status :: 4 - Beta
Requires-Python: >=3.5
Requires-Dist: odoo13-addon-sale-coupon-commercial-partner-applicability
Requires-Dist: odoo13-addon-sale-coupon-order-pending
Requires-Dist: odoo <13.1dev,>=13.0a
